norerun/__init__.py
norerun-1.0.1.dist-info/LICENSE
norerun-1.0.1.dist-info/METADATA
norerun-1.0.1.dist-info/WHEEL
norerun-1.0.1.dist-info/top_level.txt
norerun-1.0.1.dist-info/RECORD
