Metadata-Version: 2.1
Name: norerun
Version: 1.0.1
Summary: Backup to store results of functions, so they do not need to be rerun
Home-page: https://github.com/aLahat/norerun/issues
Author: Albert
Author-email: lahat.albert@gmail.com
License: UNKNOWN
Project-URL: Bug Tracker, https://github.com/aLahat/norerun/issues
Platform: UNKNOWN
Classifier: Programming Language :: Python :: 3
Classifier: License :: OSI Approved :: MIT License
Classifier: Operating System :: OS Independent
Requires-Python: >=3.6
License-File: LICENSE
